tklife/__init__.py
tklife/__main__.py
tklife/behaviors/__init__.py
tklife/behaviors/commands.py
tklife/constants.py
tklife/controller.py
tklife/core.py
tklife/dynamic.py
tklife/event.py
tklife/menu.py
tklife/menu.pyi
tklife/proxy.py
tklife/py.typed
tklife/style/__init__.py
tklife/style/progressbar.py
tklife/style/scale.py
tklife/style/scrollbar.py
tklife/style/style.py
tklife/types.py
tklife/widgets.py
tklife-2.5.0.dev3.dist-info/LICENSE
tklife-2.5.0.dev3.dist-info/METADATA
tklife-2.5.0.dev3.dist-info/WHEEL
tklife-2.5.0.dev3.dist-info/RECORD
