Metadata-Version: 2.3
Name: tklife
Version: 2.5.0.dev3
Summary: Make Tk life easier
License: MIT
Author: Cory Laughlin
Author-email: corylcomposinger@gmail.com
Requires-Python: >=3.9,<4.0
Classifier: License :: OSI Approved :: MIT License
Classifier: Programming Language :: Python :: 3
Classifier: Programming Language :: Python :: 3.9
Classifier: Programming Language :: Python :: 3.10
Classifier: Programming Language :: Python :: 3.11
Classifier: Programming Language :: Python :: 3.12
Classifier: Programming Language :: Python :: 3.13
